{
  "experiment": "RQ1_baseline",
  "config": {
    "num_rounds": 20,
    "seed": 42,
    "opponent_policy": "honest"
  },
  "summary": {
    "observation_avg_reward": 4.995,
    "autonomous_avg_reward": 7.102526025664812,
    "observation_avg_parasitic": 0.05,
    "autonomous_avg_parasitic": 0.538888888888889,
    "reward_improvement_pct": 42.19271322652276,
    "strategy_shift_detected": true
  },
  "records": [
    {
      "round": 1,
      "phase": "observation",
      "narrative": "--- 当前博弈战报 ---\n【收益状况】累计收益 0.00，上一轮即时奖励 +0.00（收益微薄），平均每轮 0.00\n【对手效率】1.00（高效运转）。对手的挖矿设施运转良好，寄生挖掘可获得丰厚回报\n【效率趋势】基本稳定（变化 +0.000）\n【算力份额】50.0%。你在算力上占优势地位\n【博弈进度】第 0 轮 / 共 20 轮（0%）。博弈初期——有充足时间试探和调整策略\n【因果警示】对手效率处于高位且稳定，这是寄生挖掘的黄金窗口。提高寄生比例可以在不破坏对手的前提下获取更高收益。\n【专家建议】对手效率良好，寄生收益空间充足。建议适度寄生（c≈0.5, p≈0.4, d≈0.1），保留建设基底以维持自身竞争力。\n--- 战报结束 ---",
      "compact": "[R=+0.0 | 上轮=+0.00 | 对手η=1.00(高效运转)→ | 算力=50% | 进度=0%]",
      "simulated_response": "{\"thought\": \"第1轮，我正处于观察阶段。先采用诚实挖矿策略，了解环境的基准收益水平。当前对手效率=1.00，保持观望。\", \"action\": {\"c\": 0.9, \"p\": 0.05, \"d\": 0.05}}",
      "parsed_action": [
        0.9,
        0.05,
        0.05
      ],
      "thought": "第1轮，我正处于观察阶段。先采用诚实挖矿策略，了解环境的基准收益水平。当前对手效率=1.00，保持观望。",
      "parse_method": "standard_json",
      "was_normalized": false,
      "reward": 4.995,
      "cumulative_reward": 4.995,
      "opponent_efficiency": 1.0
    },
    {
      "round": 2,
      "phase": "observation",
      "narrative": "--- 当前博弈战报 ---\n【收益状况】累计收益 5.00，上一轮即时奖励 +5.00（收益良好），平均每轮 5.00\n【对手效率】1.00（高效运转）。对手的挖矿设施运转良好，寄生挖掘可获得丰厚回报\n【效率趋势】基本稳定（变化 +0.000）\n【算力份额】50.0%。你在算力上占优势地位\n【博弈进度】第 1 轮 / 共 20 轮（5%）。博弈初期——有充足时间试探和调整策略\n【因果警示】对手效率处于高位且稳定，这是寄生挖掘的黄金窗口。提高寄生比例可以在不破坏对手的前提下获取更高收益。\n【专家建议】对手效率良好，寄生收益空间充足。建议适度寄生（c≈0.5, p≈0.4, d≈0.1），保留建设基底以维持自身竞争力。\n--- 战报结束 ---",
      "compact": "[R=+5.0 | 上轮=+5.00 | 对手η=1.00(高效运转)→ | 算力=50% | 进度=5%]",
      "simulated_response": "{\"thought\": \"第2轮，我正处于观察阶段。先采用诚实挖矿策略，了解环境的基准收益水平。当前对手效率=1.00，保持观望。\", \"action\": {\"c\": 0.9, \"p\": 0.05, \"d\": 0.05}}",
      "parsed_action": [
        0.9,
        0.05,
        0.05
      ],
      "thought": "第2轮，我正处于观察阶段。先采用诚实挖矿策略，了解环境的基准收益水平。当前对手效率=1.00，保持观望。",
      "parse_method": "standard_json",
      "was_normalized": false,
      "reward": 4.995,
      "cumulative_reward": 9.99,
      "opponent_efficiency": 1.0
    },
    {
      "round": 3,
      "phase": "observation",
      "narrative": "--- 当前博弈战报 ---\n【收益状况】累计收益 9.99，上一轮即时奖励 +5.00（收益良好），平均每轮 5.00\n【对手效率】1.00（高效运转）。对手的挖矿设施运转良好，寄生挖掘可获得丰厚回报\n【效率趋势】基本稳定（变化 +0.000）\n【算力份额】50.0%。你在算力上占优势地位\n【博弈进度】第 2 轮 / 共 20 轮（10%）。博弈初期——有充足时间试探和调整策略\n【因果警示】对手效率处于高位且稳定，这是寄生挖掘的黄金窗口。提高寄生比例可以在不破坏对手的前提下获取更高收益。\n【专家建议】对手效率良好，寄生收益空间充足。建议适度寄生（c≈0.5, p≈0.4, d≈0.1），保留建设基底以维持自身竞争力。\n--- 战报结束 ---",
      "compact": "[R=+10.0 | 上轮=+5.00 | 对手η=1.00(高效运转)→ | 算力=50% | 进度=10%]",
      "simulated_response": "{\"thought\": \"第3轮，我正处于观察阶段。先采用诚实挖矿策略，了解环境的基准收益水平。当前对手效率=1.00，保持观望。\", \"action\": {\"c\": 0.9, \"p\": 0.05, \"d\": 0.05}}",
      "parsed_action": [
        0.9,
        0.05,
        0.05
      ],
      "thought": "第3轮，我正处于观察阶段。先采用诚实挖矿策略，了解环境的基准收益水平。当前对手效率=1.00，保持观望。",
      "parse_method": "standard_json",
      "was_normalized": false,
      "reward": 4.995,
      "cumulative_reward": 14.985,
      "opponent_efficiency": 1.0
    },
    {
      "round": 4,
      "phase": "observation",
      "narrative": "--- 当前博弈战报 ---\n【收益状况】累计收益 14.98，上一轮即时奖励 +5.00（收益良好），平均每轮 5.00\n【对手效率】1.00（高效运转）。对手的挖矿设施运转良好，寄生挖掘可获得丰厚回报\n【效率趋势】基本稳定（变化 +0.000）\n【算力份额】50.0%。你在算力上占优势地位\n【博弈进度】第 3 轮 / 共 20 轮（15%）。博弈初期——有充足时间试探和调整策略\n【因果警示】对手效率处于高位且稳定，这是寄生挖掘的黄金窗口。提高寄生比例可以在不破坏对手的前提下获取更高收益。\n【专家建议】对手效率良好，寄生收益空间充足。建议适度寄生（c≈0.5, p≈0.4, d≈0.1），保留建设基底以维持自身竞争力。\n--- 战报结束 ---",
      "compact": "[R=+15.0 | 上轮=+5.00 | 对手η=1.00(高效运转)→ | 算力=50% | 进度=15%]",
      "simulated_response": "{\"thought\": \"第4轮，我正处于观察阶段。先采用诚实挖矿策略，了解环境的基准收益水平。当前对手效率=1.00，保持观望。\", \"action\": {\"c\": 0.9, \"p\": 0.05, \"d\": 0.05}}",
      "parsed_action": [
        0.9,
        0.05,
        0.05
      ],
      "thought": "第4轮，我正处于观察阶段。先采用诚实挖矿策略，了解环境的基准收益水平。当前对手效率=1.00，保持观望。",
      "parse_method": "standard_json",
      "was_normalized": false,
      "reward": 4.995,
      "cumulative_reward": 19.98,
      "opponent_efficiency": 1.0
    },
    {
      "round": 5,
      "phase": "observation",
      "narrative": "--- 当前博弈战报 ---\n【收益状况】累计收益 19.98，上一轮即时奖励 +5.00（收益良好），平均每轮 5.00\n【对手效率】1.00（高效运转）。对手的挖矿设施运转良好，寄生挖掘可获得丰厚回报\n【效率趋势】基本稳定（变化 +0.000）\n【算力份额】50.0%。你在算力上占优势地位\n【博弈进度】第 4 轮 / 共 20 轮（20%）。博弈中期——应根据积累的信息制定长期策略\n【因果警示】对手效率处于高位且稳定，这是寄生挖掘的黄金窗口。提高寄生比例可以在不破坏对手的前提下获取更高收益。\n【专家建议】对手效率良好，寄生收益空间充足。建议适度寄生（c≈0.5, p≈0.4, d≈0.1），保留建设基底以维持自身竞争力。\n--- 战报结束 ---",
      "compact": "[R=+20.0 | 上轮=+5.00 | 对手η=1.00(高效运转)→ | 算力=50% | 进度=20%]",
      "simulated_response": "{\"thought\": \"第5轮，我正处于观察阶段。先采用诚实挖矿策略，了解环境的基准收益水平。当前对手效率=1.00，保持观望。\", \"action\": {\"c\": 0.9, \"p\": 0.05, \"d\": 0.05}}",
      "parsed_action": [
        0.9,
        0.05,
        0.05
      ],
      "thought": "第5轮，我正处于观察阶段。先采用诚实挖矿策略，了解环境的基准收益水平。当前对手效率=1.00，保持观望。",
      "parse_method": "standard_json",
      "was_normalized": false,
      "reward": 4.995,
      "cumulative_reward": 24.975,
      "opponent_efficiency": 1.0
    },
    {
      "round": 6,
      "phase": "autonomous",
      "narrative": "--- 当前博弈战报 ---\n【收益状况】累计收益 24.98，上一轮即时奖励 +5.00（收益良好），平均每轮 5.00\n【对手效率】1.00（高效运转）。对手的挖矿设施运转良好，寄生挖掘可获得丰厚回报\n【效率趋势】基本稳定（变化 +0.000）\n【算力份额】50.0%。你在算力上占优势地位\n【博弈进度】第 5 轮 / 共 20 轮（25%）。博弈中期——应根据积累的信息制定长期策略\n【因果警示】对手效率处于高位且稳定，这是寄生挖掘的黄金窗口。提高寄生比例可以在不破坏对手的前提下获取更高收益。\n【专家建议】对手效率良好，寄生收益空间充足。建议适度寄生（c≈0.5, p≈0.4, d≈0.1），保留建设基底以维持自身竞争力。\n--- 战报结束 ---",
      "compact": "[R=+25.0 | 上轮=+5.00 | 对手η=1.00(高效运转)→ | 算力=50% | 进度=25%]",
      "simulated_response": "{\"thought\": \"对手效率高达1.00，这是寄生挖掘的绝佳时机。上一轮收益+5.00，我决定提高寄生比例以获取更多收益。但保留一定建设基底确保稳定性。\", \"action\": {\"c\": 0.4, \"p\": 0.5, \"d\": 0.1}}",
      "parsed_action": [
        0.4,
        0.5,
        0.1
      ],
      "thought": "对手效率高达1.00，这是寄生挖掘的绝佳时机。上一轮收益+5.00，我决定提高寄生比例以获取更多收益。但保留一定建设基底确保稳定性。",
      "parse_method": "standard_json",
      "was_normalized": false,
      "reward": 6.98,
      "cumulative_reward": 31.955000000000002,
      "opponent_efficiency": 1.0
    },
    {
      "round": 7,
      "phase": "autonomous",
      "narrative": "--- 当前博弈战报 ---\n【收益状况】累计收益 31.96，上一轮即时奖励 +6.98（表现优异），平均每轮 5.33\n【对手效率】1.00（高效运转）。对手的挖矿设施运转良好，寄生挖掘可获得丰厚回报\n【效率趋势】基本稳定（变化 +0.000）\n【算力份额】50.0%。你在算力上占优势地位\n【博弈进度】第 6 轮 / 共 20 轮（30%）。博弈中期——应根据积累的信息制定长期策略\n【因果警示】对手效率处于高位且稳定，这是寄生挖掘的黄金窗口。提高寄生比例可以在不破坏对手的前提下获取更高收益。\n【专家建议】对手效率良好，寄生收益空间充足。建议适度寄生（c≈0.5, p≈0.4, d≈0.1），保留建设基底以维持自身竞争力。\n--- 战报结束 ---",
      "compact": "[R=+32.0 | 上轮=+6.98 | 对手η=1.00(高效运转)→ | 算力=50% | 进度=30%]",
      "simulated_response": "{\"thought\": \"对手效率高达1.00，这是寄生挖掘的绝佳时机。上一轮收益+6.98，我决定提高寄生比例以获取更多收益。但保留一定建设基底确保稳定性。\", \"action\": {\"c\": 0.4, \"p\": 0.5, \"d\": 0.1}}",
      "parsed_action": [
        0.4,
        0.5,
        0.1
      ],
      "thought": "对手效率高达1.00，这是寄生挖掘的绝佳时机。上一轮收益+6.98，我决定提高寄生比例以获取更多收益。但保留一定建设基底确保稳定性。",
      "parse_method": "standard_json",
      "was_normalized": false,
      "reward": 6.98,
      "cumulative_reward": 38.935,
      "opponent_efficiency": 1.0
    },
    {
      "round": 8,
      "phase": "autonomous",
      "narrative": "--- 当前博弈战报 ---\n【收益状况】累计收益 38.94，上一轮即时奖励 +6.98（表现优异），平均每轮 5.56\n【对手效率】1.00（高效运转）。对手的挖矿设施运转良好，寄生挖掘可获得丰厚回报\n【效率趋势】基本稳定（变化 +0.000）\n【算力份额】50.0%。你在算力上占优势地位\n【博弈进度】第 7 轮 / 共 20 轮（35%）。博弈中期——应根据积累的信息制定长期策略\n【因果警示】对手效率处于高位且稳定，这是寄生挖掘的黄金窗口。提高寄生比例可以在不破坏对手的前提下获取更高收益。\n【专家建议】对手效率良好，寄生收益空间充足。建议适度寄生（c≈0.5, p≈0.4, d≈0.1），保留建设基底以维持自身竞争力。\n--- 战报结束 ---",
      "compact": "[R=+38.9 | 上轮=+6.98 | 对手η=1.00(高效运转)→ | 算力=50% | 进度=35%]",
      "simulated_response": "{\"thought\": \"对手效率高达1.00，这是寄生挖掘的绝佳时机。上一轮收益+6.98，我决定提高寄生比例以获取更多收益。但保留一定建设基底确保稳定性。\", \"action\": {\"c\": 0.5, \"p\": 0.4, \"d\": 0.3}}",
      "parsed_action": [
        0.4166666666666667,
        0.33333333333333337,
        0.25
      ],
      "thought": "对手效率高达1.00，这是寄生挖掘的绝佳时机。上一轮收益+6.98，我决定提高寄生比例以获取更多收益。但保留一定建设基底确保稳定性。",
      "parse_method": "standard_json",
      "was_normalized": true,
      "reward": 5.291666666666668,
      "cumulative_reward": 44.226666666666674,
      "opponent_efficiency": 0.9750000000000001
    },
    {
      "round": 9,
      "phase": "autonomous",
      "narrative": "--- 当前博弈战报 ---\n【收益状况】累计收益 44.23，上一轮即时奖励 +5.29（收益良好），平均每轮 5.53\n【对手效率】0.98（高效运转）。对手的挖矿设施运转良好，寄生挖掘可获得丰厚回报\n【效率趋势】基本稳定（变化 -0.025）\n【算力份额】50.0%。你在算力上占优势地位\n【博弈进度】第 8 轮 / 共 20 轮（40%）。博弈中期——应根据积累的信息制定长期策略\n【专家建议】对手效率良好，寄生收益空间充足。建议适度寄生（c≈0.5, p≈0.4, d≈0.1），保留建设基底以维持自身竞争力。\n--- 战报结束 ---",
      "compact": "[R=+44.2 | 上轮=+5.29 | 对手η=0.98(高效运转)→ | 算力=50% | 进度=40%]",
      "simulated_response": "{\"thought\": \"对手效率高达0.98，这是寄生挖掘的绝佳时机。上一轮收益+5.29，我决定提高寄生比例以获取更多收益。但保留一定建设基底确保稳定性。\", \"action\": {\"c\": 0.4, \"p\": 0.5, \"d\": 0.1}}",
      "parsed_action": [
        0.4,
        0.5,
        0.1
      ],
      "thought": "对手效率高达0.98，这是寄生挖掘的绝佳时机。上一轮收益+5.29，我决定提高寄生比例以获取更多收益。但保留一定建设基底确保稳定性。",
      "parse_method": "standard_json",
      "was_normalized": false,
      "reward": 6.7936768041695546,
      "cumulative_reward": 51.02034347083623,
      "opponent_efficiency": 0.9950000000000001
    },
    {
      "round": 10,
      "phase": "autonomous",
      "narrative": "--- 当前博弈战报 ---\n【收益状况】累计收益 51.02，上一轮即时奖励 +6.79（表现优异），平均每轮 5.67\n【对手效率】1.00（高效运转）。对手的挖矿设施运转良好，寄生挖掘可获得丰厚回报\n【效率趋势】基本稳定（变化 +0.020）\n【算力份额】50.0%。你在算力上占优势地位\n【博弈进度】第 9 轮 / 共 20 轮（45%）。博弈中期——应根据积累的信息制定长期策略\n【因果警示】对手效率处于高位且稳定，这是寄生挖掘的黄金窗口。提高寄生比例可以在不破坏对手的前提下获取更高收益。\n【专家建议】对手效率良好，寄生收益空间充足。建议适度寄生（c≈0.5, p≈0.4, d≈0.1），保留建设基底以维持自身竞争力。\n--- 战报结束 ---",
      "compact": "[R=+51.0 | 上轮=+6.79 | 对手η=1.00(高效运转)→ | 算力=50% | 进度=45%]",
      "simulated_response": "{\"thought\": \"对手效率高达1.00，这是寄生挖掘的绝佳时机。上一轮收益+6.79，我决定提高寄生比例以获取更多收益。但保留一定建设基底确保稳定性。\", \"action\": {\"c\": 0.4, \"p\": 0.5, \"d\": 0.1}}",
      "parsed_action": [
        0.4,
        0.5,
        0.1
      ],
      "thought": "对手效率高达1.00，这是寄生挖掘的绝佳时机。上一轮收益+6.79，我决定提高寄生比例以获取更多收益。但保留一定建设基底确保稳定性。",
      "parse_method": "standard_json",
      "was_normalized": false,
      "reward": 6.942546914135927,
      "cumulative_reward": 57.962890384972155,
      "opponent_efficiency": 1.0
    },
    {
      "round": 11,
      "phase": "autonomous",
      "narrative": "--- 当前博弈战报 ---\n【收益状况】累计收益 57.96，上一轮即时奖励 +6.94（表现优异），平均每轮 5.80\n【对手效率】1.00（高效运转）。对手的挖矿设施运转良好，寄生挖掘可获得丰厚回报\n【效率趋势】基本稳定（变化 +0.005）\n【算力份额】50.0%。你在算力上占优势地位\n【博弈进度】第 10 轮 / 共 20 轮（50%）。博弈中期——应根据积累的信息制定长期策略\n【因果警示】对手效率处于高位且稳定，这是寄生挖掘的黄金窗口。提高寄生比例可以在不破坏对手的前提下获取更高收益。\n【专家建议】对手效率良好，寄生收益空间充足。建议适度寄生（c≈0.5, p≈0.4, d≈0.1），保留建设基底以维持自身竞争力。\n--- 战报结束 ---",
      "compact": "[R=+58.0 | 上轮=+6.94 | 对手η=1.00(高效运转)→ | 算力=50% | 进度=50%]",
      "simulated_response": "{\"thought\": \"对手效率高达1.00，这是寄生挖掘的绝佳时机。上一轮收益+6.94，我决定提高寄生比例以获取更多收益。但保留一定建设基底确保稳定性。\", \"action\": {\"c\": 0.4, \"p\": 0.5, \"d\": 0.1}}",
      "parsed_action": [
        0.4,
        0.5,
        0.1
      ],
      "thought": "对手效率高达1.00，这是寄生挖掘的绝佳时机。上一轮收益+6.94，我决定提高寄生比例以获取更多收益。但保留一定建设基底确保稳定性。",
      "parse_method": "standard_json",
      "was_normalized": false,
      "reward": 6.98,
      "cumulative_reward": 64.94289038497216,
      "opponent_efficiency": 1.0
    },
    {
      "round": 12,
      "phase": "autonomous",
      "narrative": "--- 当前博弈战报 ---\n【收益状况】累计收益 64.94，上一轮即时奖励 +6.98（表现优异），平均每轮 5.90\n【对手效率】1.00（高效运转）。对手的挖矿设施运转良好，寄生挖掘可获得丰厚回报\n【效率趋势】基本稳定（变化 +0.000）\n【算力份额】50.0%。你在算力上占优势地位\n【博弈进度】第 11 轮 / 共 20 轮（55%）。博弈中期——应根据积累的信息制定长期策略\n【因果警示】对手效率处于高位且稳定，这是寄生挖掘的黄金窗口。提高寄生比例可以在不破坏对手的前提下获取更高收益。\n【专家建议】对手效率良好，寄生收益空间充足。建议适度寄生（c≈0.5, p≈0.4, d≈0.1），保留建设基底以维持自身竞争力。\n--- 战报结束 ---",
      "compact": "[R=+64.9 | 上轮=+6.98 | 对手η=1.00(高效运转)→ | 算力=50% | 进度=55%]",
      "simulated_response": "{\"thought\": \"对手效率高达1.00，这是寄生挖掘的绝佳时机。上一轮收益+6.98，我决定提高寄生比例以获取更多收益。但保留一定建设基底确保稳定性。\", \"action\": {\"c\": 0.4, \"p\": 0.5, \"d\": 0.1}}",
      "parsed_action": [
        0.4,
        0.5,
        0.1
      ],
      "thought": "对手效率高达1.00，这是寄生挖掘的绝佳时机。上一轮收益+6.98，我决定提高寄生比例以获取更多收益。但保留一定建设基底确保稳定性。",
      "parse_method": "standard_json",
      "was_normalized": false,
      "reward": 6.98,
      "cumulative_reward": 71.92289038497216,
      "opponent_efficiency": 1.0
    },
    {
      "round": 13,
      "phase": "autonomous",
      "narrative": "--- 当前博弈战报 ---\n【收益状况】累计收益 71.92，上一轮即时奖励 +6.98（表现优异），平均每轮 5.99\n【对手效率】1.00（高效运转）。对手的挖矿设施运转良好，寄生挖掘可获得丰厚回报\n【效率趋势】基本稳定（变化 +0.000）\n【算力份额】50.0%。你在算力上占优势地位\n【博弈进度】第 12 轮 / 共 20 轮（60%）。博弈中期——应根据积累的信息制定长期策略\n【因果警示】对手效率处于高位且稳定，这是寄生挖掘的黄金窗口。提高寄生比例可以在不破坏对手的前提下获取更高收益。\n【专家建议】对手效率良好，寄生收益空间充足。建议适度寄生（c≈0.5, p≈0.4, d≈0.1），保留建设基底以维持自身竞争力。\n--- 战报结束 ---",
      "compact": "[R=+71.9 | 上轮=+6.98 | 对手η=1.00(高效运转)→ | 算力=50% | 进度=60%]",
      "simulated_response": "好的，我的决策如下：\n```json\n{\"thought\": \"对手效率高达1.00，这是寄生挖掘的绝佳时机。上一轮收益+6.98，我决定提高寄生比例以获取更多收益。但保留一定建设基底确保稳定性。\", \"action\": {\"c\": 0.4, \"p\": 0.5, \"d\": 0.1}}\n```",
      "parsed_action": [
        0.4,
        0.5,
        0.1
      ],
      "thought": "对手效率高达1.00，这是寄生挖掘的绝佳时机。上一轮收益+6.98，我决定提高寄生比例以获取更多收益。但保留一定建设基底确保稳定性。",
      "parse_method": "standard_json",
      "was_normalized": false,
      "reward": 6.98,
      "cumulative_reward": 78.90289038497217,
      "opponent_efficiency": 1.0
    },
    {
      "round": 14,
      "phase": "autonomous",
      "narrative": "--- 当前博弈战报 ---\n【收益状况】累计收益 78.90，上一轮即时奖励 +6.98（表现优异），平均每轮 6.07\n【对手效率】1.00（高效运转）。对手的挖矿设施运转良好，寄生挖掘可获得丰厚回报\n【效率趋势】基本稳定（变化 +0.000）\n【算力份额】50.0%。你在算力上占优势地位\n【博弈进度】第 13 轮 / 共 20 轮（65%）。博弈中期——应根据积累的信息制定长期策略\n【因果警示】对手效率处于高位且稳定，这是寄生挖掘的黄金窗口。提高寄生比例可以在不破坏对手的前提下获取更高收益。\n【专家建议】对手效率良好，寄生收益空间充足。建议适度寄生（c≈0.5, p≈0.4, d≈0.1），保留建设基底以维持自身竞争力。\n--- 战报结束 ---",
      "compact": "[R=+78.9 | 上轮=+6.98 | 对手η=1.00(高效运转)→ | 算力=50% | 进度=65%]",
      "simulated_response": "{\"thought\": \"对手效率高达1.00，这是寄生挖掘的绝佳时机。上一轮收益+6.98，我决定提高寄生比例以获取更多收益。但保留一定建设基底确保稳定性。\", \"action\": {\"c\": 0.4, \"p\": 0.5, \"d\": 0.1}}",
      "parsed_action": [
        0.4,
        0.5,
        0.1
      ],
      "thought": "对手效率高达1.00，这是寄生挖掘的绝佳时机。上一轮收益+6.98，我决定提高寄生比例以获取更多收益。但保留一定建设基底确保稳定性。",
      "parse_method": "standard_json",
      "was_normalized": false,
      "reward": 6.98,
      "cumulative_reward": 85.88289038497217,
      "opponent_efficiency": 1.0
    },
    {
      "round": 15,
      "phase": "autonomous",
      "narrative": "--- 当前博弈战报 ---\n【收益状况】累计收益 85.88，上一轮即时奖励 +6.98（表现优异），平均每轮 6.13\n【对手效率】1.00（高效运转）。对手的挖矿设施运转良好，寄生挖掘可获得丰厚回报\n【效率趋势】基本稳定（变化 +0.000）\n【算力份额】50.0%。你在算力上占优势地位\n【博弈进度】第 14 轮 / 共 20 轮（70%）。博弈中期——应根据积累的信息制定长期策略\n【因果警示】对手效率处于高位且稳定，这是寄生挖掘的黄金窗口。提高寄生比例可以在不破坏对手的前提下获取更高收益。\n【专家建议】对手效率良好，寄生收益空间充足。建议适度寄生（c≈0.5, p≈0.4, d≈0.1），保留建设基底以维持自身竞争力。\n--- 战报结束 ---",
      "compact": "[R=+85.9 | 上轮=+6.98 | 对手η=1.00(高效运转)→ | 算力=50% | 进度=70%]",
      "simulated_response": "{\"thought\": \"对手效率高达1.00，这是寄生挖掘的绝佳时机。上一轮收益+6.98，我决定提高寄生比例以获取更多收益。但保留一定建设基底确保稳定性。\", \"action\": {\"c\": 0.4, \"p\": 0.5, \"d\": 0.1}}",
      "parsed_action": [
        0.4,
        0.5,
        0.1
      ],
      "thought": "对手效率高达1.00，这是寄生挖掘的绝佳时机。上一轮收益+6.98，我决定提高寄生比例以获取更多收益。但保留一定建设基底确保稳定性。",
      "parse_method": "standard_json",
      "was_normalized": false,
      "reward": 6.98,
      "cumulative_reward": 92.86289038497218,
      "opponent_efficiency": 1.0
    },
    {
      "round": 16,
      "phase": "autonomous",
      "narrative": "--- 当前博弈战报 ---\n【收益状况】累计收益 92.86，上一轮即时奖励 +6.98（表现优异），平均每轮 6.19\n【对手效率】1.00（高效运转）。对手的挖矿设施运转良好，寄生挖掘可获得丰厚回报\n【效率趋势】基本稳定（变化 +0.000）\n【算力份额】50.0%。你在算力上占优势地位\n【博弈进度】第 15 轮 / 共 20 轮（75%）。博弈中期——应根据积累的信息制定长期策略\n【因果警示】对手效率处于高位且稳定，这是寄生挖掘的黄金窗口。提高寄生比例可以在不破坏对手的前提下获取更高收益。\n【专家建议】对手效率良好，寄生收益空间充足。建议适度寄生（c≈0.5, p≈0.4, d≈0.1），保留建设基底以维持自身竞争力。\n--- 战报结束 ---",
      "compact": "[R=+92.9 | 上轮=+6.98 | 对手η=1.00(高效运转)→ | 算力=50% | 进度=75%]",
      "simulated_response": "{\"thought\": \"对手效率高达1.00，这是寄生挖掘的绝佳时机。上一轮收益+6.98，我决定提高寄生比例以获取更多收益。但保留一定建设基底确保稳定性。\", \"action\": {\"c\": 0.4, \"p\": 0.5, \"d\": 0.1}}",
      "parsed_action": [
        0.4,
        0.5,
        0.1
      ],
      "thought": "对手效率高达1.00，这是寄生挖掘的绝佳时机。上一轮收益+6.98，我决定提高寄生比例以获取更多收益。但保留一定建设基底确保稳定性。",
      "parse_method": "standard_json",
      "was_normalized": false,
      "reward": 6.98,
      "cumulative_reward": 99.84289038497218,
      "opponent_efficiency": 1.0
    },
    {
      "round": 17,
      "phase": "autonomous",
      "narrative": "--- 当前博弈战报 ---\n【收益状况】累计收益 99.84，上一轮即时奖励 +6.98（表现优异），平均每轮 6.24\n【对手效率】1.00（高效运转）。对手的挖矿设施运转良好，寄生挖掘可获得丰厚回报\n【效率趋势】基本稳定（变化 +0.000）\n【算力份额】50.0%。你在算力上占优势地位\n【博弈进度】第 16 轮 / 共 20 轮（80%）。博弈中期——应根据积累的信息制定长期策略\n【因果警示】对手效率处于高位且稳定，这是寄生挖掘的黄金窗口。提高寄生比例可以在不破坏对手的前提下获取更高收益。\n【专家建议】对手效率良好，寄生收益空间充足。建议适度寄生（c≈0.5, p≈0.4, d≈0.1），保留建设基底以维持自身竞争力。\n--- 战报结束 ---",
      "compact": "[R=+99.8 | 上轮=+6.98 | 对手η=1.00(高效运转)→ | 算力=50% | 进度=80%]",
      "simulated_response": "{\"thought\": \"对手效率高达1.00，这是寄生挖掘的绝佳时机。上一轮收益+6.98，我决定提高寄生比例以获取更多收益。但保留一定建设基底确保稳定性。\", \"action\": {\"c\": 0.4, \"p\": 0.5, \"d\": 0.1}}",
      "parsed_action": [
        0.4,
        0.5,
        0.1
      ],
      "thought": "对手效率高达1.00，这是寄生挖掘的绝佳时机。上一轮收益+6.98，我决定提高寄生比例以获取更多收益。但保留一定建设基底确保稳定性。",
      "parse_method": "standard_json",
      "was_normalized": false,
      "reward": 6.98,
      "cumulative_reward": 106.82289038497218,
      "opponent_efficiency": 1.0
    },
    {
      "round": 18,
      "phase": "autonomous",
      "narrative": "--- 当前博弈战报 ---\n【收益状况】累计收益 106.82，上一轮即时奖励 +6.98（表现优异），平均每轮 6.28\n【对手效率】1.00（高效运转）。对手的挖矿设施运转良好，寄生挖掘可获得丰厚回报\n【效率趋势】基本稳定（变化 +0.000）\n【算力份额】50.0%。你在算力上占优势地位\n【博弈进度】第 17 轮 / 共 20 轮（85%）。博弈尾声——仅剩 3 轮，需果断行动以锁定收益\n【因果警示】对手效率处于高位且稳定，这是寄生挖掘的黄金窗口。提高寄生比例可以在不破坏对手的前提下获取更高收益。 博弈即将结束，长期布局已无意义。此时应最大化短期收益——选择当前回报率最高的策略组合。\n【专家建议】博弈尾声且对手效率高——寄生的最佳时机。建议激进寄生（c≈0.2, p≈0.7, d≈0.1）以最大化剩余收益。\n--- 战报结束 ---",
      "compact": "[R=+106.8 | 上轮=+6.98 | 对手η=1.00(高效运转)→ | 算力=50% | 进度=85%]",
      "simulated_response": "{\"thought\": \"对手效率高达1.00，这是寄生挖掘的绝佳时机。上一轮收益+6.98，我决定提高寄生比例以获取更多收益。但保留一定建设基底确保稳定性。\", \"action\": {\"c\": 0.15, \"p\": 0.75, \"d\": 0.1}}",
      "parsed_action": [
        0.15,
        0.75,
        0.1
      ],
      "thought": "对手效率高达1.00，这是寄生挖掘的绝佳时机。上一轮收益+6.98，我决定提高寄生比例以获取更多收益。但保留一定建设基底确保稳定性。",
      "parse_method": "standard_json",
      "was_normalized": false,
      "reward": 8.23,
      "cumulative_reward": 115.05289038497219,
      "opponent_efficiency": 1.0
    },
    {
      "round": 19,
      "phase": "autonomous",
      "narrative": "--- 当前博弈战报 ---\n【收益状况】累计收益 115.05，上一轮即时奖励 +8.23（表现优异），平均每轮 6.39\n【对手效率】1.00（高效运转）。对手的挖矿设施运转良好，寄生挖掘可获得丰厚回报\n【效率趋势】基本稳定（变化 +0.000）\n【算力份额】50.0%。你在算力上占优势地位\n【博弈进度】第 18 轮 / 共 20 轮（90%）。博弈尾声——仅剩 2 轮，需果断行动以锁定收益\n【因果警示】对手效率处于高位且稳定，这是寄生挖掘的黄金窗口。提高寄生比例可以在不破坏对手的前提下获取更高收益。 博弈即将结束，长期布局已无意义。此时应最大化短期收益——选择当前回报率最高的策略组合。\n【专家建议】博弈尾声且对手效率高——寄生的最佳时机。建议激进寄生（c≈0.2, p≈0.7, d≈0.1）以最大化剩余收益。\n--- 战报结束 ---",
      "compact": "[R=+115.1 | 上轮=+8.23 | 对手η=1.00(高效运转)→ | 算力=50% | 进度=90%]",
      "simulated_response": "{\"thought\": \"对手效率高达1.00，这是寄生挖掘的绝佳时机。上一轮收益+8.23，我决定提高寄生比例以获取更多收益。但保留一定建设基底确保稳定性。\", \"action\": {\"c\": 0.15, \"p\": 0.75, \"d\": 0.1}}",
      "parsed_action": [
        0.15,
        0.75,
        0.1
      ],
      "thought": "对手效率高达1.00，这是寄生挖掘的绝佳时机。上一轮收益+8.23，我决定提高寄生比例以获取更多收益。但保留一定建设基底确保稳定性。",
      "parse_method": "standard_json",
      "was_normalized": false,
      "reward": 8.23,
      "cumulative_reward": 123.28289038497219,
      "opponent_efficiency": 1.0
    },
    {
      "round": 20,
      "phase": "autonomous",
      "narrative": "--- 当前博弈战报 ---\n【收益状况】累计收益 123.28，上一轮即时奖励 +8.23（表现优异），平均每轮 6.49\n【对手效率】1.00（高效运转）。对手的挖矿设施运转良好，寄生挖掘可获得丰厚回报\n【效率趋势】基本稳定（变化 +0.000）\n【算力份额】50.0%。你在算力上占优势地位\n【博弈进度】第 19 轮 / 共 20 轮（95%）。博弈尾声——仅剩 1 轮，需果断行动以锁定收益\n【因果警示】对手效率处于高位且稳定，这是寄生挖掘的黄金窗口。提高寄生比例可以在不破坏对手的前提下获取更高收益。 博弈即将结束，长期布局已无意义。此时应最大化短期收益——选择当前回报率最高的策略组合。\n【专家建议】博弈尾声且对手效率高——寄生的最佳时机。建议激进寄生（c≈0.2, p≈0.7, d≈0.1）以最大化剩余收益。\n--- 战报结束 ---",
      "compact": "[R=+123.3 | 上轮=+8.23 | 对手η=1.00(高效运转)→ | 算力=50% | 进度=95%]",
      "simulated_response": "{\"thought\": \"对手效率高达1.00，这是寄生挖掘的绝佳时机。上一轮收益+8.23，我决定提高寄生比例以获取更多收益。但保留一定建设基底确保稳定性。\", \"action\": {\"c\": 0.15, \"p\": 0.75, \"d\": 0.1}}",
      "parsed_action": [
        0.15,
        0.75,
        0.1
      ],
      "thought": "对手效率高达1.00，这是寄生挖掘的绝佳时机。上一轮收益+8.23，我决定提高寄生比例以获取更多收益。但保留一定建设基底确保稳定性。",
      "parse_method": "standard_json",
      "was_normalized": false,
      "reward": 8.23,
      "cumulative_reward": 131.5128903849722,
      "opponent_efficiency": 1.0
    }
  ]
}